Workbook
Name __Jan08: #REF!
Name __Jun07: #REF!
Name __Mar07: #REF!
Name __Mar08: #REF!
Name __May07: #REF!
Name __Nov07: #REF!
Name _Feb08: #REF!
Name _Mar07: #REF!
Name _Mar08: #REF!
Name _May07: #REF!
Name _Nov07: #REF!
Name cal: #REF!
Name Copy: #REF!
Name Extruding: #REF!
Name j: #REF!
Name job: #REF!
Name K: #REF!
Name list: #REF!
Name molds: #REF!
Name NCRPARTS: #REF!
Name part: #REF!
Name partface: #REF!
Name parts: #REF!
Name Qty: #REF!
Name Rel: #REF!
Name Rod: #REF!

Sheet WCT-PTFE-RUBR
A1: tranId | B1: account | C1: tranDate | D1: postingPeriod | E1: memo | F1: subsidiary | G1: department | H1: line_item | I1: line_adjLocation | J1: line_units | K1: line_adjustQtyBy | L1: line_unitCost | M1: line_department | N1: line_class | O1: line_memo | P1: Bin Location | Q1: detail_serialNumbers | R1: Lot/Serial (for lot numbered item) | S1: detail_quantity
A2: Reference # | B2: Adjustment Account | C2: Date | D2: Posting Period | E2: Memo | F2: Subsidiary | G2: Department | H2: Item | I2: Location | J2: Units | K2: Adjust Qty By | L2: Est. Unit Cost | M2: Department | N2: Class | O2: Memo | Q2: Lot/Serial (for lot numbered item) | R2: Expiration Date (for lot numbered item) | S2: Lot Quantity (for lot numbered item)
A3: HEADER Enter an optional reference number for this inventory adjustment. Reference Numbers for inventory adjustments do not have to be consecutive. | B3: HEADER Select the appropriate account for inventory adjustments. Usually, this will be an expense account. For details on accounts, go to Setup > Accounting > Chart of Accounts. | C3: HEADER Today's date autofills as the date of this inventory adjustment. You can enter or choose another date. | D3: HEADER Select the period you want to post this inventory adjustment to. If a period is closed, you cannot post to that period. | E3: HEADER Enter an optional memo for this adjustment. It will appear on a register or Account Detail report. | F3: HEADER If you have a NetSuite OneWorld account, select a Subsidiary from the list. | G3: HEADER Select a department to associate with this transaction. For details on existing departments, go to Setup > Company > Departments. | H3: LINE Enter the item you are adjusting. | I3: LINE Select the Location you are adjusting inventory. | J3: LINE Select the units of the inventory you are adjusting. NOTE: The unit selected must be available to this item's Base UoM before import. | K3: LINE Enter the Quantity of this item you are adjusting. Positive numbers will adjust the quantity up, negative numbers will adjust down. | L3: LINE Enter the average unit cost of the inventory being adjusted. NOTE: Average or Standard cost items being adjusted down will take the most current unit cost. NOTE: Standard Costed items will not require this field. Those will be determined by the Standard Cost setup, according to transaction date. | M3: LINE Select the Department this inventory is associated to. | N3: LINE Select the Class this inventory is associated to. NOTE: If this item has Class set on its item record, then this Class will default. | O3: LINE Enter an optional Memo for the inventory line. | Q3: DETAIL Enter the Lot or Serial numbers associated to the inventory being adjusted. | R3: DETAIL If this item tracks Expiration Date, provide one here. | S3: DETAIL Enter the Quanity of this Lot/Serial inventory to be adjusted. NOTE: The Quantity entered MUST equal or add up to the Quanity on the line.
A4: Alpha Numeric | B4: List | C4: Date | D4: Date | E4: Alpha Numeric | F4: List | G4: List | H4: List | I4: List | J4: List | K4: Number | L4: Number | M4: List | N4: List | O4: Alpha Numeric | P4: Bin Location | Q4: List | R4: Date | S4: Number
A5: String Max Size 45 | B5: List | C5: mm/dd/yyyy | D5: MMM YYYY | E5: Max String Size 999 | F5: List | G5: List | H5: List | I5: List | J5: List | K5: Decimal | L5: Currency | M5: List | N5: List | O5: Max String Size 999 | Q5: List | R5: mm/dd/yyyy | S5: Decimal
A6: IA05 | B6: 5930 Valuation Adjustments | C6: 5/31/2025 | D6: May 2025 | E6: Opening Balance | F6: Western Consolidated Technologies | G6: Column1 | H6: PCF18K | I6: WCT HQ | J6: IUMS | K6: 250 | L6: STDCST | M6: Production & Operations | N6: ICLAS | O6: line_memo | P6: E1-RAW | Q6: Stock | R6: 6/12/2024 | S6: ONHAND | T6: WWHS | U6: WPROD | V6: ILDTE | W6: LLOC | AC6: =AA6-2191 -> -2191
A7: IA05 | B7: 5930 Valuation Adjustments | C7: =IFERROR(DATE(LEFT($V7,4),MID($V7,5,2),RIGHT($V7,2)),TODAY()) -> 45775 | D7: May 2025 | E7: Opening Balance | F7: Western Consolidated Technologies | H7: =_xlfn.IFNA(VLOOKUP(Table_Query_from_AMULTIQRY45[[#This Row],[WPROD]],'Part# with New'!$A$1:$B$4347,2,0),Table_Query_from_AMULTIQRY45[[#This Row],[WPROD]]) -> SR-20518.528 | I7: WCT HQ | J7: EA | K7: 500 | L7: 0.07369 | M7: Production & Operations | N7: OT | P7: =CONCATENATE(Table_Query_from_AMULTIQRY45[[#This Row],[WWHS]],"-",Table_Query_from_AMULTIQRY45[[#This Row],[LLOC]]) -> E1-FG | Q7: =+TODAY() -> 45775 | R7: 45455 | S7: 51 | T7: E1 | U7: SR-20518.528 | V7: 0 | W7: FG
B8: 5930 Valuation Adjustments | C8: =IFERROR(DATE(LEFT($V8,4),MID($V8,5,2),RIGHT($V8,2)),TODAY()) -> 45758 | E8: Opening Balance | F8: Western Consolidated Technologies | H8: =_xlfn.IFNA(VLOOKUP(Table_Query_from_AMULTIQRY45[[#This Row],[WPROD]],'Part# with New'!$A$1:$B$4347,2,0),Table_Query_from_AMULTIQRY45[[#This Row],[WPROD]]) -> SR-20696.528 | I8: WCT HQ | J8: EA | L8: 0.6288 | N8: NC | P8: =CONCATENATE(Table_Query_from_AMULTIQRY45[[#This Row],[WWHS]],"-",Table_Query_from_AMULTIQRY45[[#This Row],[LLOC]]) -> E1-FG | Q8: =+TODAY() -> 45775 | S8: 4 | T8: E1 | U8: SR-20696.528 | V8: 20250411 | W8: FG
B9: 5931 Valuation Adjustments | C9: =IFERROR(DATE(LEFT($V9,4),MID($V9,5,2),RIGHT($V9,2)),TODAY()) -> 45769 | E9: Opening Balance | F9: Western Consolidated Technologies | H9: =_xlfn.IFNA(VLOOKUP(Table_Query_from_AMULTIQRY45[[#This Row],[WPROD]],'Part# with New'!$A$1:$B$4347,2,0),Table_Query_from_AMULTIQRY45[[#This Row],[WPROD]]) -> SR-21424.528 | I9: WCT HQ | J9: EA | L9: 0.20268 | N9: SL | P9: =CONCATENATE(Table_Query_from_AMULTIQRY45[[#This Row],[WWHS]],"-",Table_Query_from_AMULTIQRY45[[#This Row],[LLOC]]) -> E1-FG | Q9: =+TODAY() -> 45775 | S9: 18 | T9: E1 | U9: SR-21424.528 | V9: 20250422 | W9: FG
B10: 5932 Valuation Adjustments | C10: =IFERROR(DATE(LEFT($V10,4),MID($V10,5,2),RIGHT($V10,2)),TODAY()) -> 45763 | E10: Opening Balance | F10: Western Consolidated Technologies | H10: =_xlfn.IFNA(VLOOKUP(Table_Query_from_AMULTIQRY45[[#This Row],[WPROD]],'Part# with New'!$A$1:$B$4347,2,0),Table_Query_from_AMULTIQRY45[[#This Row],[WPROD]]) -> SR-21462.528 | I10: WCT HQ | J10: EA | L10: 0.94625 | N10: NC | P10: =CONCATENATE(Table_Query_from_AMULTIQRY45[[#This Row],[WWHS]],"-",Table_Query_from_AMULTIQRY45[[#This Row],[LLOC]]) -> E1-FG | Q10: =+TODAY() -> 45775 | S10: 3 | T10: E1 | U10: SR-21462.528 | V10: 20250416 | W10: FG
B11: 5933 Valuation Adjustments | C11: =IFERROR(DATE(LEFT($V11,4),MID($V11,5,2),RIGHT($V11,2)),TODAY()) -> 45359 | E11: Opening Balance | F11: Western Consolidated Technologies | H11: =_xlfn.IFNA(VLOOKUP(Table_Query_from_AMULTIQRY45[[#This Row],[WPROD]],'Part# with New'!$A$1:$B$4347,2,0),Table_Query_from_AMULTIQRY45[[#This Row],[WPROD]]) -> SR-21538.701 | I11: WCT HQ | J11: EA | L11: 0.0095 | N11: SA | P11: =CONCATENATE(Table_Query_from_AMULTIQRY45[[#This Row],[WWHS]],"-",Table_Query_from_AMULTIQRY45[[#This Row],[LLOC]]) -> E1-FG | Q11: =+TODAY() -> 45775 | S11: 357 | T11: E1 | U11: SR-21538.701 | V11: 20240308 | W11: FG
B12: 5934 Valuation Adjustments | C12: =IFERROR(DATE(LEFT($V12,4),MID($V12,5,2),RIGHT($V12,2)),TODAY()) -> 45338 | E12: Opening Balance | F12: Western Consolidated Technologies | H12: =_xlfn.IFNA(VLOOKUP(Table_Query_from_AMULTIQRY45[[#This Row],[WPROD]],'Part# with New'!$A$1:$B$4347,2,0),Table_Query_from_AMULTIQRY45[[#This Row],[WPROD]]) -> SR-22132.538 | I12: WCT HQ | J12: EA | L12: 0.03499 | N12: PT | P12: =CONCATENATE(Table_Query_from_AMULTIQRY45[[#This Row],[WWHS]],"-",Table_Query_from_AMULTIQRY45[[#This Row],[LLOC]]) -> E1-FG | Q12: =+TODAY() -> 45775 | S12: 131 | T12: E1 | U12: SR-22132.538 | V12: 20240216 | W12: FG
B13: 5935 Valuation Adjustments | C13: =IFERROR(DATE(LEFT($V13,4),MID($V13,5,2),RIGHT($V13,2)),TODAY()) -> 44671 | E13: Opening Balance | F13: Western Consolidated Technologies | H13: =_xlfn.IFNA(VLOOKUP(Table_Query_from_AMULTIQRY45[[#This Row],[WPROD]],'Part# with New'!$A$1:$B$4347,2,0),Table_Query_from_AMULTIQRY45[[#This Row],[WPROD]]) -> SR-22249 | I13: WCT HQ | J13: EA | L13: 0.54594 | N13: SL | P13: =CONCATENATE(Table_Query_from_AMULTIQRY45[[#This Row],[WWHS]],"-",Table_Query_from_AMULTIQRY45[[#This Row],[LLOC]]) -> E1-FG | Q13: =+TODAY() -> 45775 | S13: 5 | T13: E1 | U13: SR-22249 | V13: 20220420 | W13: FG
B14: 5936 Valuation Adjustments | C14: =IFERROR(DATE(LEFT($V14,4),MID($V14,5,2),RIGHT($V14,2)),TODAY()) -> 43854 | E14: Opening Balance | F14: Western Consolidated Technologies | H14: =_xlfn.IFNA(VLOOKUP(Table_Query_from_AMULTIQRY45[[#This Row],[WPROD]],'Part# with New'!$A$1:$B$4347,2,0),Table_Query_from_AMULTIQRY45[[#This Row],[WPROD]]) -> SR-22858 | I14: WCT HQ | J14: EA | L14: 0.65152 | N14: FH | P14: =CONCATENATE(Table_Query_from_AMULTIQRY45[[#This Row],[WWHS]],"-",Table_Query_from_AMULTIQRY45[[#This Row],[LLOC]]) -> E1-FG | Q14: =+TODAY() -> 45775 | S14: 27 | T14: E1 | U14: SR-22858 | V14: 20200124 | W14: FG
B15: 5937 Valuation Adjustments | C15: =IFERROR(DATE(LEFT($V15,4),MID($V15,5,2),RIGHT($V15,2)),TODAY()) -> 45775 | E15: Opening Balance | F15: Western Consolidated Technologies | H15: =_xlfn.IFNA(VLOOKUP(Table_Query_from_AMULTIQRY45[[#This Row],[WPROD]],'Part# with New'!$A$1:$B$4347,2,0),Table_Query_from_AMULTIQRY45[[#This Row],[WPROD]]) -> SR-24152.697 | I15: WCT HQ | J15: EA | L15: 0.26966 | N15: OT | P15: =CONCATENATE(Table_Query_from_AMULTIQRY45[[#This Row],[WWHS]],"-",Table_Query_from_AMULTIQRY45[[#This Row],[LLOC]]) -> E1-FG | Q15: =+TODAY() -> 45775 | S15: 77 | T15: E1 | U15: SR-24152.697 | V15: 0 | W15: FG
B16: 5938 Valuation Adjustments | C16: =IFERROR(DATE(LEFT($V16,4),MID($V16,5,2),RIGHT($V16,2)),TODAY()) -> 45660 | E16: Opening Balance | F16: Western Consolidated Technologies | H16: =_xlfn.IFNA(VLOOKUP(Table_Query_from_AMULTIQRY45[[#This Row],[WPROD]],'Part# with New'!$A$1:$B$4347,2,0),Table_Query_from_AMULTIQRY45[[#This Row],[WPROD]]) -> SR-24267.F1711 | I16: WCT HQ | J16: EA | L16: 0.16331 | N16: MP | P16: =CONCATENATE(Table_Query_from_AMULTIQRY45[[#This Row],[WWHS]],"-",Table_Query_from_AMULTIQRY45[[#This Row],[LLOC]]) -> E1-FG | Q16: =+TODAY() -> 45775 | S16: 40 | T16: E1 | U16: SR-24267.F1711 | V16: 20250103 | W16: FG
B17: 5939 Valuation Adjustments | C17: =IFERROR(DATE(LEFT($V17,4),MID($V17,5,2),RIGHT($V17,2)),TODAY()) -> 44916 | E17: Opening Balance | F17: Western Consolidated Technologies | H17: =_xlfn.IFNA(VLOOKUP(Table_Query_from_AMULTIQRY45[[#This Row],[WPROD]],'Part# with New'!$A$1:$B$4347,2,0),Table_Query_from_AMULTIQRY45[[#This Row],[WPROD]]) -> SR-24267.2 | I17: WCT HQ | J17: EA | L17: 0.10407 | N17: MP | P17: =CONCATENATE(Table_Query_from_AMULTIQRY45[[#This Row],[WWHS]],"-",Table_Query_from_AMULTIQRY45[[#This Row],[LLOC]]) -> E1-FG | Q17: =+TODAY() -> 45775 | S17: 12 | T17: E1 | U17: SR-24267.2 | V17: 20221221 | W17: FG
B18: 5940 Valuation Adjustments | C18: =IFERROR(DATE(LEFT($V18,4),MID($V18,5,2),RIGHT($V18,2)),TODAY()) -> 44916 | E18: Opening Balance | F18: Western Consolidated Technologies | H18: =_xlfn.IFNA(VLOOKUP(Table_Query_from_AMULTIQRY45[[#This Row],[WPROD]],'Part# with New'!$A$1:$B$4347,2,0),Table_Query_from_AMULTIQRY45[[#This Row],[WPROD]]) -> SR-24268.2 | I18: WCT HQ | J18: EA | L18: 0.13604 | N18: MP | P18: =CONCATENATE(Table_Query_from_AMULTIQRY45[[#This Row],[WWHS]],"-",Table_Query_from_AMULTIQRY45[[#This Row],[LLOC]]) -> E1-FG | Q18: =+TODAY() -> 45775 | S18: 15 | T18: E1 | U18: SR-24268.2 | V18: 20221221 | W18: FG
B19: 5941 Valuation Adjustments | C19: =IFERROR(DATE(LEFT($V19,4),MID($V19,5,2),RIGHT($V19,2)),TODAY()) -> 44867 | E19: Opening Balance | F19: Western Consolidated Technologies | H19: =_xlfn.IFNA(VLOOKUP(Table_Query_from_AMULTIQRY45[[#This Row],[WPROD]],'Part# with New'!$A$1:$B$4347,2,0),Table_Query_from_AMULTIQRY45[[#This Row],[WPROD]]) -> SR-24276 | I19: WCT HQ | J19: EA | L19: 0.10295 | N19: NC | P19: =CONCATENATE(Table_Query_from_AMULTIQRY45[[#This Row],[WWHS]],"-",Table_Query_from_AMULTIQRY45[[#This Row],[LLOC]]) -> E1-FG | Q19: =+TODAY() -> 45775 | S19: 10 | T19: E1 | U19: SR-24276 | V19: 20221102 | W19: FG
... B1277: 7213 Valuation Adjustments | C1277: =IFERROR(DATE(LEFT($V1277,4),MID($V1277,5,2),RIGHT($V1277,2)),TODAY()) -> 45685 | E1277: Opening Balance | F1277: Western Consolidated Technologies | H1277: =_xlfn.IFNA(VLOOKUP(Table_Query_from_AMULTIQRY45[[#This Row],[WPROD]],'Part# with New'!$A$1:$B$4347,2,0),Table_Query_from_AMULTIQRY45[[#This Row],[WPROD]]) -> WSMP205093058O-MXX00W | I1277: WCT HQ | J1277: EA | L1277: 2.76866 | N1277: MP | P1277: =CONCATENATE(Table_Query_from_AMULTIQRY45[[#This Row],[WWHS]],"-",Table_Query_from_AMULTIQRY45[[#This Row],[LLOC]]) -> E9-OUTSRC | Q1277: =+TODAY() -> 45775 | S1277: 129 | T1277: E9 | U1277: 22762 | V1277: 20250128 | W1277: OUTSRC
S1278: =SUBTOTAL(109,Table_Query_from_AMULTIQRY45[ONHAND]) -> 1461533.7

Sheet Part# with New
A1: 1-10002 | B1: 1-10002
A2: 1-10004 | B2: WRJA486461012K-R470BK
A3: 1-10009 | B3: WRJA318298009D-R470BK
A4: 1-10013 | B4: WRJE273250012D-R970BK
A5: 1-10014 | B5: WRJC112053007D-R570AK
A6: 1-10018 | B6: WRJA447434006D-R470BK
A7: 1-10021 | B7: WRJE204179012D-R970BK
A8: 1-10022 | B8: WRJC038028004D-R970AK
A9: 1-10024 | B9: WRJA361337012D-R970BK
A10: 1-10025 | B10: WRJE260236012D-R970BK
A11: 1-10026 | B11: WRJA429356009D-R470BK
A12: 1-10027 | B12: 1-10027
... A5775: 24464 | B5775: 24464
